{"BaseModel.e1bd634a-8177-43e5-903c-7551c7d940be": {"id": "e1bd634a-8177-43e5-903c-7551c7d940be", "created_at": "2023-12-10T17:45:29.991123", "updated_at": "2023-12-10T17:45:29.991147", "name": "My_First_Model", "my_number": 89, "__class__": "BaseModel"}, "BaseModel.872f7815-dda2-4e14-9044-cba1adfa4e63": {"id": "872f7815-dda2-4e14-9044-cba1adfa4e63", "created_at": "2023-12-10T17:45:37.792476", "updated_at": "2023-12-10T17:45:37.792499", "name": "My_First_Model", "my_number": 89, "__class__": "BaseModel"}, "BaseModel.76f7d220-f3c8-4550-aeb7-2dfc579eaf02": {"id": "76f7d220-f3c8-4550-aeb7-2dfc579eaf02", "created_at": "2023-12-10T17:45:42.800408", "updated_at": "2023-12-10T17:45:42.800429", "name": "My_First_Model", "my_number": 89, "__class__": "BaseModel"}}